vincaweb/__init__.py
vincaweb/routes.py
vincaweb/templates/basic_action_links.tpl
vincaweb/templates/edit.tpl
vincaweb/templates/home_filter_form.tpl
vincaweb/templates/preview_basic.tpl
vincaweb/templates/review_basic.tpl
vincaweb/templates/review_verses.tpl
vincaweb-0.1.1.dist-info/WHEEL
vincaweb-0.1.1.dist-info/METADATA
vincaweb-0.1.1.dist-info/RECORD
