Metadata-Version: 2.1
Name: vincaweb
Version: 0.1.1
Summary: 
License: CC0
Author: Oscar Laird
Author-email: olaird25@gmail.com
Requires-Python: >=3.8,<4.0
Classifier: License :: Other/Proprietary License
Classifier: Programming Language :: Python :: 3
Classifier: Programming Language :: Python :: 3.10
Classifier: Programming Language :: Python :: 3.8
Classifier: Programming Language :: Python :: 3.9
Requires-Dist: Flask (>=2.1.2,<3.0.0)
Requires-Dist: vinca (>=2.4.7,<3.0.0)
